Topsis/__init__.py
Topsis/setup.py
Topsis/topsis.py
Topsis1/__init__.py
Topsis1/topsis.py
Topsis_Harsh_102203964-1.0.0.dist-info/LICENCE.txt
Topsis_Harsh_102203964-1.0.0.dist-info/METADATA
Topsis_Harsh_102203964-1.0.0.dist-info/WHEEL
Topsis_Harsh_102203964-1.0.0.dist-info/entry_points.txt
Topsis_Harsh_102203964-1.0.0.dist-info/top_level.txt
Topsis_Harsh_102203964-1.0.0.dist-info/RECORD
