Metadata-Version: 2.2
Name: Topsis-Harsh-102203964
Version: 1.0.0
Summary: A Python package for implementing TOPSIS
Home-page: https://github.com/Harsh-tyagi94/Topsis
Author: Harsh Tyagi
Author-email: htyagi_be22@thapar.edu
Classifier: Programming Language :: Python :: 3
Classifier: License :: OSI Approved :: MIT License
License-File: LICENCE.txt
Requires-Dist: numpy
Requires-Dist: pandas
Dynamic: author
Dynamic: author-email
Dynamic: classifier
Dynamic: description
Dynamic: description-content-type
Dynamic: home-page
Dynamic: requires-dist
Dynamic: summary
